vcoml/__init__.py
vcoml/__main__.py
vcoml/packer.py
vcoml/unpacker.py
vcoml-1.0.1.dist-info/LICENSE
vcoml-1.0.1.dist-info/WHEEL
vcoml-1.0.1.dist-info/METADATA
vcoml-1.0.1.dist-info/RECORD
