Metadata-Version: 2.1
Name: vcoml
Version: 1.0.1
Summary: Imagine a markup language, but worse
Home-page: https://github.com/vcokltfre/vcoml
License: MIT
Author: vcokltfre
Author-email: vcokltfre@gmail.com
Requires-Python: >=3.10,<4.0
Classifier: License :: OSI Approved :: MIT License
Classifier: Programming Language :: Python :: 3
Classifier: Programming Language :: Python :: 3.10
Project-URL: Repository, https://github.com/vcokltfre/vcoml
